mkdocs_gitlab_review/__init__.py
mkdocs_gitlab_review/plugin.py
mkdocs_gitlab_review_plugin-1.0.2.dist-info/LICENSE
mkdocs_gitlab_review_plugin-1.0.2.dist-info/METADATA
mkdocs_gitlab_review_plugin-1.0.2.dist-info/NOTICE
mkdocs_gitlab_review_plugin-1.0.2.dist-info/WHEEL
mkdocs_gitlab_review_plugin-1.0.2.dist-info/entry_points.txt
mkdocs_gitlab_review_plugin-1.0.2.dist-info/top_level.txt
mkdocs_gitlab_review_plugin-1.0.2.dist-info/RECORD
