Metadata-Version: 2.1
Name: mkdocs-gitlab-review-plugin
Version: 1.0.2
Summary: Use gitlab visual review with mkdocs.
Home-page: https://github.com/intergral/mkdocs-gitlab-review-plugin/
Author: Ben Donnelly
Author-email: support@nerd.vision
License: Apache 2.0
Keywords: mkdocs python markdown gitlab
Platform: UNKNOWN
Classifier: Development Status :: 5 - Production/Stable
Classifier: Intended Audience :: Developers
Classifier: Intended Audience :: Information Technology
Classifier: License :: OSI Approved :: MIT License
Classifier: Programming Language :: Python
Classifier: Programming Language :: Python :: 3 :: Only
Classifier: Programming Language :: Python :: 3.5
Requires-Python: >=3.5
Requires-Dist: mkdocs (>=1.1.2)
Provides-Extra: test
